subconscious/README.md
subconscious/__init__.py
subconscious/client.py
subconscious/grammar.py
subconscious/tim_api.py
subconscious/tim_pydantic.py
subconscious_python-0.1.22.dist-info/licenses/LICENSE
subconscious_python-0.1.22.dist-info/METADATA
subconscious_python-0.1.22.dist-info/WHEEL
subconscious_python-0.1.22.dist-info/top_level.txt
subconscious_python-0.1.22.dist-info/RECORD
