Metadata-Version: 2.4
Name: subconscious-python
Version: 0.1.22
Summary: Python SDK for Subconscious AI agent framework
Author-email: Subconscious Systems <hongyin@subconscious.dev>
License-Expression: MIT
Project-URL: Homepage, https://subconscious.dev
Project-URL: Documentation, https://docs.subconscious.dev
Project-URL: Repository, https://github.com/subconscious-systems/TIMRUN
Project-URL: Issues, https://github.com/subconscious-systems/TIMRUN/issues
Keywords: ai,agent,framework,structured-output,reasoning
Classifier: Development Status :: 3 - Alpha
Classifier: Intended Audience :: Developers
Classifier: Programming Language :: Python :: 3
Classifier: Programming Language :: Python :: 3.8
Classifier: Programming Language :: Python :: 3.9
Classifier: Programming Language :: Python :: 3.10
Classifier: Programming Language :: Python :: 3.11
Classifier: Programming Language :: Python :: 3.12
Classifier: Topic :: Software Development :: Libraries :: Python Modules
Classifier: Topic :: Scientific/Engineering :: Artificial Intelligence
Requires-Python: >=3.8
License-File: LICENSE
Requires-Dist: pydantic>=2.0.0
Requires-Dist: openai>=1.0.0
Requires-Dist: requests>=2.25.0
Requires-Dist: pyhumps>=3.0.0
Requires-Dist: typing-extensions>=4.0.0
Provides-Extra: dev
Requires-Dist: pytest>=7.0.0; extra == "dev"
Requires-Dist: pytest-cov>=4.0.0; extra == "dev"
Requires-Dist: black>=22.0.0; extra == "dev"
Requires-Dist: isort>=5.0.0; extra == "dev"
Requires-Dist: flake8>=4.0.0; extra == "dev"
Requires-Dist: mypy>=1.0.0; extra == "dev"
Dynamic: license-file
